LICENSE
MANIFEST.in
README.md
VERSION
setup.cfg
setup.py
das7pad_dns_lexicon.egg-info/PKG-INFO
das7pad_dns_lexicon.egg-info/SOURCES.txt
das7pad_dns_lexicon.egg-info/dependency_links.txt
das7pad_dns_lexicon.egg-info/entry_points.txt
das7pad_dns_lexicon.egg-info/requires.txt
das7pad_dns_lexicon.egg-info/top_level.txt
lexicon/__init__.py
lexicon/cli.py
lexicon/client.py
lexicon/config.py
lexicon/conftest.py
lexicon/discovery.py
lexicon/parser.py
lexicon/providers/__init__.py
lexicon/providers/aliyun.py
lexicon/providers/aurora.py
lexicon/providers/auto.py
lexicon/providers/azure.py
lexicon/providers/base.py
lexicon/providers/cloudflare.py
lexicon/providers/cloudns.py
lexicon/providers/cloudxns.py
lexicon/providers/conoha.py
lexicon/providers/constellix.py
lexicon/providers/digitalocean.py
lexicon/providers/dinahosting.py
lexicon/providers/directadmin.py
lexicon/providers/dnsimple.py
lexicon/providers/dnsmadeeasy.py
lexicon/providers/dnspark.py
lexicon/providers/dnspod.py
lexicon/providers/dreamhost.py
lexicon/providers/dynu.py
lexicon/providers/easydns.py
lexicon/providers/easyname.py
lexicon/providers/euserv.py
lexicon/providers/exoscale.py
lexicon/providers/gandi.py
lexicon/providers/gehirn.py
lexicon/providers/glesys.py
lexicon/providers/godaddy.py
lexicon/providers/googleclouddns.py
lexicon/providers/gransy.py
lexicon/providers/gratisdns.py
lexicon/providers/henet.py
lexicon/providers/hetzner.py
lexicon/providers/hostingde.py
lexicon/providers/hover.py
lexicon/providers/infoblox.py
lexicon/providers/internetbs.py
lexicon/providers/inwx.py
lexicon/providers/linode.py
lexicon/providers/linode4.py
lexicon/providers/localzone.py
lexicon/providers/luadns.py
lexicon/providers/memset.py
lexicon/providers/namecheap.py
lexicon/providers/namesilo.py
lexicon/providers/netcup.py
lexicon/providers/nfsn.py
lexicon/providers/nsone.py
lexicon/providers/onapp.py
lexicon/providers/online.py
lexicon/providers/ovh.py
lexicon/providers/plesk.py
lexicon/providers/pointhq.py
lexicon/providers/powerdns.py
lexicon/providers/rackspace.py
lexicon/providers/rage4.py
lexicon/providers/rcodezero.py
lexicon/providers/route53.py
lexicon/providers/safedns.py
lexicon/providers/sakuracloud.py
lexicon/providers/softlayer.py
lexicon/providers/subreg.py
