Metadata-Version: 2.1
Name: das7pad-dns-lexicon
Version: 3.3.27.post2
Summary: Manipulate DNS records on various DNS providers in a standardized/agnostic way
Home-page: https://github.com/AnalogJ/lexicon
Author: Jason Kulatunga
Author-email: jason@thesparktree.com
License: MIT
Keywords: dns lexicon dns-lexicon dehydrated letsencrypt aliyun aurora auto azure cloudflare cloudns cloudxns conoha constellix digitalocean dinahosting directadmin dnsimple dnsmadeeasy dnspark dnspod dreamhost dynu easydns easyname euserv exoscale gandi gehirn glesys godaddy googleclouddns gransy gratisdns henet hetzner hostingde hover infoblox internetbs inwx linode linode4 localzone luadns memset namecheap namesilo netcup nfsn nsone onapp online ovh plesk pointhq powerdns rackspace rage4 rcod
Platform: UNKNOWN
Classifier: Development Status :: 5 - Production/Stable
Classifier: Intended Audience :: Developers
Classifier: Intended Audience :: System Administrators
Classifier: Topic :: Software Development :: Libraries :: Python Modules
Classifier: Topic :: Internet :: Name Service (DNS)
Classifier: Topic :: System :: Systems Administration
Classifier: Topic :: Utilities
Classifier: License :: OSI Approved :: MIT License
Classifier: Programming Language :: Python :: 2
Classifier: Programming Language :: Python :: 2.7
Classifier: Programming Language :: Python :: 3
Classifier: Programming Language :: Python :: 3.5
Classifier: Programming Language :: Python :: 3.6
Classifier: Programming Language :: Python :: 3.7
Classifier: Programming Language :: Python :: 3.8
Requires-Python: >=2.7, !=3.0.*, !=3.1.*, !=3.2.*, !=3.3.*, !=3.4.*
Provides-Extra: namecheap
Provides-Extra: route53
Provides-Extra: softlayer
Provides-Extra: subreg
Provides-Extra: gransy
Provides-Extra: transip
Provides-Extra: plesk
Provides-Extra: henet
Provides-Extra: easyname
Provides-Extra: localzone
Provides-Extra: gratisdns
Provides-Extra: dev
Provides-Extra: full
